{
  "isa": {
    "holdings": {
      "ig_isa": [
        {
          "ticker": "LON:MNG",
          "name": "M&G PLC",
          "shares": 3916,
          "book_cost": 8026.66,
          "live_price": 2.6457,
          "value": 10360.5612,
          "gain_value": 2333.9012000000002,
          "gain_percentage": 29.07686634291225,
          "annual_dividend_per_share": 0.2,
          "annual_div_yield": 7.559436066069471,
          "annual_income": 783.2,
          "sector": "Financials",
          "last_updated": "2025-11-20 15:55:09",
          "fair_value": "3.7500",
          "discount_pct": "29.45%",
          "rating": "BUY✅"
        },
        {
          "ticker": "LON:VOD",
          "name": "Vodafone Group PLC",
          "shares": 7658,
          "book_cost": 6500.31,
          "live_price": 0.901,
          "value": 6899.858,
          "gain_value": 399.5479999999998,
          "gain_percentage": 6.146599162193799,
          "annual_dividend_per_share": 0.05,
          "annual_div_yield": 5.549389567147614,
          "annual_income": 382.90000000000003,
          "sector": "Communications",
          "last_updated": "2025-11-20 15:55:09",
          "fair_value": "0.9500",
          "discount_pct": "5.16%",
          "rating": "HOLD🟠"
        },
        {
          "ticker": "LON:BP",
          "name": "BP PLC",
          "shares": 707,
          "book_cost": 2890.99,
          "live_price": 4.574,
          "value": 3233.8179999999998,
          "gain_value": 342.828,
          "gain_percentage": 11.85849829989035,
          "annual_dividend_per_share": 0.27,
          "annual_div_yield": 5.90292960209882,
          "annual_income": 190.89000000000001,
          "sector": "Energy",
          "last_updated": "2025-11-20 15:55:09",
          "fair_value": "6.6000",
          "discount_pct": "30.70%",
          "rating": "BUY✅"
        },
        {
          "ticker": "LON:NG",
          "name": "National Grid",
          "shares": 192,
          "book_cost": 1983.01,
          "live_price": 11.44,
          "value": 2196.48,
          "gain_value": 213.47000000000003,
          "gain_percentage": 10.764948235258522,
          "annual_dividend_per_share": 0.55,
          "annual_div_yield": 4.807692307692308,
          "annual_income": 105.60000000000001,
          "sector": "Utilities",
          "last_updated": "2025-11-20 15:55:09",
          "fair_value": "11.4000",
          "discount_pct": "-0.35%",
          "rating": "WAIT⛔️"
        },
        {
          "ticker": "LON:SVT",
          "name": "Severn Trent Plc",
          "shares": 78,
          "book_cost": 1895.42,
          "live_price": 27.24,
          "value": 2124.72,
          "gain_value": 229.29999999999973,
          "gain_percentage": 12.097582593831431,
          "annual_dividend_per_share": 1.11,
          "annual_div_yield": 4.07488986784141,
          "annual_income": 86.58000000000001,
          "sector": "Utilities",
          "last_updated": "2025-11-20 15:55:09",
          "fair_value": "28.5000",
          "discount_pct": "4.42%",
          "rating": "HOLD🟠"
        },
        {
          "ticker": "LON:IUKD",
          "name": "iShares Uk Dividend UCITS ETF",
          "shares": 343,
          "book_cost": 2881.53,
          "live_price": 8.8414,
          "value": 3032.6002,
          "gain_value": 151.07019999999966,
          "gain_percentage": 5.242707867001199,
          "annual_dividend_per_share": 0.39,
          "annual_div_yield": 4.411066120750108,
          "annual_income": 133.77,
          "sector": "ETF/Financials",
          "last_updated": "2025-11-20 15:55:09",
          "fair_value": "9.4000",
          "discount_pct": "5.94%",
          "rating": "HOLD🟠"
        },
        {
          "ticker": "LON:LAND",
          "name": "Land Securities",
          "shares": 317,
          "book_cost": 1763.47,
          "live_price": 5.882,
          "value": 1864.5939999999998,
          "gain_value": 101.1239999999998,
          "gain_percentage": 5.734375974640895,
          "annual_dividend_per_share": 0.38,
          "annual_div_yield": 6.460387623257397,
          "annual_income": 120.46000000000001,
          "sector": "Real Estate",
          "last_updated": "2025-11-20 15:55:09",
          "fair_value": "7.8000",
          "discount_pct": "24.59%",
          "rating": "BUY✅"
        },
        {
          "ticker": "LON:PHNX",
          "name": "Phoenix Group Holdings",
          "shares": 1467,
          "book_cost": 9604.35,
          "live_price": 6.575,
          "value": 9645.525,
          "gain_value": 41.17499999999927,
          "gain_percentage": 0.42871198987957826,
          "annual_dividend_per_share": 0.52,
          "annual_div_yield": 7.90874524714829,
          "annual_income": 762.84,
          "sector": "Fianacials",
          "last_updated": "2025-11-20 15:55:09",
          "fair_value": "6.5000",
          "discount_pct": "-1.15%",
          "rating": "WAIT⛔️"
        },
        {
          "ticker": "LON:LGEN",
          "name": "Legal & General Group",
          "shares": 3445,
          "book_cost": 8076.92,
          "live_price": 2.3559,
          "value": 8116.0755,
          "gain_value": 39.15549999999985,
          "gain_percentage": 0.48478256563145167,
          "annual_dividend_per_share": 0.2,
          "annual_div_yield": 8.489324674222164,
          "annual_income": 689,
          "sector": "Financials",
          "last_updated": "2025-11-20 15:55:09",
          "fair_value": "4.1000",
          "discount_pct": "42.54%",
          "rating": "BUY✅"
        },
        {
          "ticker": "LON:LLOY",
          "name": "Lloyds Banking Group PLC",
          "shares": 606,
          "book_cost": 496.92,
          "live_price": 0.8785,
          "value": 532.371,
          "gain_value": 35.450999999999965,
          "gain_percentage": 7.134146341463407,
          "annual_dividend_per_share": 0.02,
          "annual_div_yield": 2.2766078542970978,
          "annual_income": 12.120000000000001,
          "sector": "Financial",
          "last_updated": "2025-11-20 15:55:09",
          "fair_value": "0.5800",
          "discount_pct": "-51.47%",
          "rating": "NOBUY❌"
        },
        {
          "ticker": "LON:ASHM",
          "name": "Ashmore Group PLC",
          "shares": 620,
          "book_cost": 994.5,
          "live_price": 1.6068,
          "value": 996.216,
          "gain_value": 1.7160000000000082,
          "gain_percentage": 0.17254901960784397,
          "annual_dividend_per_share": 0.12,
          "annual_div_yield": 7.468259895444361,
          "annual_income": 74.39999999999999,
          "sector": "Financials",
          "last_updated": "2025-11-20 15:55:09",
          "fair_value": "1.9500",
          "discount_pct": "17.60%",
          "rating": "BUY✅"
        },
        {
          "ticker": "LON:SUPR",
          "name": "Supermarket Income REIT PLC",
          "shares": 8055,
          "book_cost": 6345.89,
          "live_price": 0.785,
          "value": 6323.175,
          "gain_value": -22.715000000000146,
          "gain_percentage": -0.3579482153015596,
          "annual_dividend_per_share": 0.08,
          "annual_div_yield": 10.19108280254777,
          "annual_income": 644.4,
          "sector": "Real Estate REIT",
          "last_updated": "2025-11-20 15:55:09",
          "fair_value": "1.0000",
          "discount_pct": "21.50%",
          "rating": "BUY✅"
        },
        {
          "ticker": "LON:BBOX",
          "name": "Tritax Big Box REIT PLC",
          "shares": 350,
          "book_cost": 496.27,
          "live_price": 1.461,
          "value": 511.35,
          "gain_value": 15.080000000000041,
          "gain_percentage": 3.0386684667620534,
          "annual_dividend_per_share": 0.08,
          "annual_div_yield": 5.475701574264202,
          "annual_income": 28,
          "sector": "Real Estate REIT",
          "last_updated": "2025-11-20 15:55:09",
          "fair_value": "1.7500",
          "discount_pct": "16.51%",
          "rating": "BUY✅"
        },
        {
          "ticker": "6XS",
          "name": "Astrid Intelligence",
          "shares": 617065,
          "book_cost": 2989.92,
          "live_price": 0.0012,
          "value": 740.478,
          "gain_value": -2249.442,
          "gain_percentage": -75.23418686787606,
          "annual_dividend_per_share": 0,
          "annual_div_yield": 0,
          "annual_income": 0,
          "sector": "Ai",
          "last_updated": "2025-11-20 15:55:09",
          "fair_value": "0.0020",
          "discount_pct": "40.00%",
          "rating": "BUY✅"
        }
      ],
      "trade212_isa": [
        {
          "ticker": "LON:PHP",
          "name": "Primary Health Properties",
          "shares": 299,
          "book_cost": 276.46,
          "live_price": 0.9425,
          "value": 281.8075,
          "gain_value": 5.347500000000025,
          "gain_percentage": 1.9342762063228043,
          "annual_dividend_per_share": 0.06,
          "annual_div_yield": 6.36604774535809,
          "annual_income": 17.939999999999998,
          "sector": "Real Estate/Healthcare REIT",
          "last_updated": "2025-11-20 15:55:09",
          "fair_value": "1.2000",
          "discount_pct": "21.46%",
          "rating": "BUY✅"
        },
        {
          "ticker": "LON:SEQI",
          "name": "Sequoia Economic Infrastructure",
          "shares": 300,
          "book_cost": 232.8,
          "live_price": 0.7907,
          "value": 237.20999999999998,
          "gain_value": 4.409999999999968,
          "gain_percentage": 1.8943298969072029,
          "annual_dividend_per_share": 0.06,
          "annual_div_yield": 7.588212975844188,
          "annual_income": 18,
          "sector": "Infrastructure REIT",
          "last_updated": "2025-11-20 15:55:09",
          "fair_value": "0.9000",
          "discount_pct": "12.14%",
          "rating": "HOLD🟠"
        },
        {
          "ticker": "LON:RGL",
          "name": "Regional REIT",
          "shares": 255.1512287,
          "book_cost": 269.95,
          "live_price": 1.0054,
          "value": 256.52904533498,
          "gain_value": -13.420954665019963,
          "gain_percentage": -4.971644624937937,
          "annual_dividend_per_share": 0.12,
          "annual_div_yield": 11.935548040580862,
          "annual_income": 30.618147443999998,
          "sector": "Real Estate REIT",
          "last_updated": "2025-11-20 15:55:09",
          "fair_value": "2.1000",
          "discount_pct": "52.12%",
          "rating": "BUY✅"
        },
        {
          "ticker": "LON:GCP",
          "name": "GCP Infrastructure Investments",
          "shares": 1000,
          "book_cost": 749,
          "live_price": 0.7035,
          "value": 703.5,
          "gain_value": -45.5,
          "gain_percentage": -6.074766355140187,
          "annual_dividend_per_share": 0.07,
          "annual_div_yield": 9.950248756218906,
          "annual_income": 70,
          "sector": "Infrastructure REIT",
          "last_updated": "2025-11-20 15:55:09",
          "fair_value": "0.9800",
          "discount_pct": "28.21%",
          "rating": "BUY✅"
        },
        {
          "ticker": "FSFL.L",
          "name": "Foresight Solar Fund",
          "shares": 1633.210858,
          "book_cost": 1223.53,
          "live_price": 0,
          "value": 0,
          "gain_value": -1223.53,
          "gain_percentage": -100,
          "annual_dividend_per_share": 0.07,
          "annual_div_yield": 0,
          "annual_income": 114.32476006,
          "sector": "Utilities/Renewable Energy",
          "last_updated": "2025-11-20 15:55:09",
          "fair_value": null,
          "discount_pct": null,
          "rating": null
        }
      ]
    },
    "dividends": {
      "last_updated": "2025-11-20 08:53:17",
      "upcoming": [
        {
          "Account": "TRADE212",
          "ticker": "PHP.L",
          "name": "Primary Health Properties ",
          "ex_div_date": "2025-10-09",
          "pay_date": "2025-11-21",
          "dividend_per_share": "0.02",
          "shares": "299",
          "shares_at_exdiv": "299.00",
          "total_dividend": "5.98",
          "dividend_received": "",
          "status": "Confirmed",
          "frequency": "Quarterly ",
          "notes": "",
          "logged_to_json": "FALSE"
        },
        {
          "Account": "TRADE212",
          "ticker": "SEQI.L",
          "name": "Sequoia Economic Infrastructure",
          "ex_div_date": "2025-10-23",
          "pay_date": "2025-11-21",
          "dividend_per_share": "0.02",
          "shares": "300",
          "shares_at_exdiv": "300.00",
          "total_dividend": "6.00",
          "dividend_received": "",
          "status": "Confirmed",
          "frequency": "Quarterly ",
          "notes": "",
          "logged_to_json": "FALSE"
        },
        {
          "Account": "IG ISA",
          "ticker": "SUPR.L",
          "name": "Supermarket Income REIT PLC",
          "ex_div_date": "2025-10-23",
          "pay_date": "2025-11-21",
          "dividend_per_share": "0.02",
          "shares": "8055",
          "shares_at_exdiv": "8,055.00",
          "total_dividend": "124.05",
          "dividend_received": "",
          "status": "Confirmed",
          "frequency": "Quarterly ",
          "notes": "",
          "logged_to_json": "FALSE"
        },
        {
          "Account": "TRADE212",
          "ticker": "FSFL.L",
          "name": "Foresight Solar Fund",
          "ex_div_date": "2025-10-30",
          "pay_date": "2025-11-24",
          "dividend_per_share": "0.02",
          "shares": "1633.219858",
          "shares_at_exdiv": "1633.219858",
          "total_dividend": "32.66",
          "dividend_received": "",
          "status": "Confirmed",
          "frequency": "Quarterly ",
          "notes": "",
          "logged_to_json": "FALSE"
        },
        {
          "Account": "IG ISA",
          "ticker": "BBOX.L",
          "name": "Tritax Big Box REIT PLC",
          "ex_div_date": "2025-11-06",
          "pay_date": "2025-11-27",
          "dividend_per_share": "0.02",
          "shares": "350",
          "shares_at_exdiv": "350.00",
          "total_dividend": "6.70",
          "dividend_received": "",
          "status": "Confirmed",
          "frequency": "Quarterly ",
          "notes": "",
          "logged_to_json": "FALSE"
        },
        {
          "Account": "IG ISA",
          "ticker": "BBOX.L",
          "name": "Tritax Big Box REIT PLC",
          "ex_div_date": "2026-03-13",
          "pay_date": "2025-11-27",
          "dividend_per_share": "",
          "shares": "350",
          "shares_at_exdiv": "350.00",
          "total_dividend": "0.00",
          "dividend_received": "",
          "status": "Estimated",
          "frequency": "Quarterly ",
          "notes": "",
          "logged_to_json": "FALSE"
        },
        {
          "Account": "IG ISA",
          "ticker": "ASHM.L",
          "name": "Ashmore Group PLC",
          "ex_div_date": "2025-11-07",
          "pay_date": "2025-12-08",
          "dividend_per_share": "0.12",
          "shares": "620",
          "shares_at_exdiv": "620.00",
          "total_dividend": "74.40",
          "dividend_received": "",
          "status": "Confirmed",
          "frequency": "Semi-Annual",
          "notes": "",
          "logged_to_json": "FALSE"
        },
        {
          "Account": "TRADE212",
          "ticker": "GCP.L",
          "name": "GCP Infrastructure ",
          "ex_div_date": "2025-11-13",
          "pay_date": "2025-12-09",
          "dividend_per_share": "0.02",
          "shares": "1000",
          "shares_at_exdiv": "1,000.00",
          "total_dividend": "20.00",
          "dividend_received": "",
          "status": "Confirmed",
          "frequency": "Quarterly ",
          "notes": "",
          "logged_to_json": "FALSE"
        },
        {
          "Account": "IG ISA",
          "ticker": "BP.L",
          "name": "BP PLC",
          "ex_div_date": "2025-11-13",
          "pay_date": "2025-12-19",
          "dividend_per_share": "0.06",
          "shares": "707",
          "shares_at_exdiv": "707.00",
          "total_dividend": "44.73",
          "dividend_received": "",
          "status": "Confirmed",
          "frequency": "Quarterly",
          "notes": "",
          "logged_to_json": "FALSE"
        },
        {
          "Account": "IG ISA",
          "ticker": "IUKD.L",
          "name": "iShares Uk Dividend UCITS ETF",
          "ex_div_date": "2025-12-12",
          "pay_date": "2025-12-26",
          "dividend_per_share": "0.09",
          "shares": "343",
          "shares_at_exdiv": "343.00",
          "total_dividend": "30.87",
          "dividend_received": "",
          "status": "Estimated",
          "frequency": "Quarterly ",
          "notes": "",
          "logged_to_json": "FALSE"
        },
        {
          "Account": "TRADE212",
          "ticker": "RGL.L",
          "name": "Regional REIT",
          "ex_div_date": "2025-11-20",
          "pay_date": "2026-01-09",
          "dividend_per_share": "0.03",
          "shares": "255.1512287",
          "shares_at_exdiv": "255.15",
          "total_dividend": "7.65",
          "dividend_received": "",
          "status": "Confirmed",
          "frequency": "Quarterly",
          "notes": "",
          "logged_to_json": "FALSE"
        },
        {
          "Account": "IG ISA",
          "ticker": "LAND.L",
          "name": "Land Securities",
          "ex_div_date": "2025-11-27",
          "pay_date": "2026-01-09",
          "dividend_per_share": "0.19",
          "shares": "317",
          "shares_at_exdiv": "317.00",
          "total_dividend": "60.23",
          "dividend_received": "",
          "status": "Confirmed",
          "frequency": "Quarterly",
          "notes": "",
          "logged_to_json": "FALSE"
        },
        {
          "Account": "IG ISA",
          "ticker": "SVT.L",
          "name": "Severn Trent Plc",
          "ex_div_date": "2025-12-01",
          "pay_date": "2026-01-09",
          "dividend_per_share": "0.47",
          "shares": "78",
          "shares_at_exdiv": "78.00",
          "total_dividend": "36.66",
          "dividend_received": "",
          "status": "Estimated",
          "frequency": "Semi-Annual",
          "notes": "",
          "logged_to_json": "FALSE"
        },
        {
          "Account": "IG ISA",
          "ticker": "NG.L",
          "name": "National Grid",
          "ex_div_date": "2025-11-20",
          "pay_date": "2026-01-13",
          "dividend_per_share": "0.16",
          "shares": "192",
          "shares_at_exdiv": "192.00",
          "total_dividend": "30.72",
          "dividend_received": "",
          "status": "Confirmed",
          "frequency": "Quarterly ",
          "notes": "",
          "logged_to_json": "FALSE"
        },
        {
          "Account": "IG ISA",
          "ticker": "VOD.L",
          "name": "Vodafone Group PLC",
          "ex_div_date": "2025-11-20",
          "pay_date": "2026-02-05",
          "dividend_per_share": "0.02",
          "shares": "7658",
          "shares_at_exdiv": "7,658.00",
          "total_dividend": "152.32",
          "dividend_received": "",
          "status": "Confirmed",
          "frequency": "Semi-Annual",
          "notes": "",
          "logged_to_json": "FALSE"
        },
        {
          "Account": "TRADE212",
          "ticker": "PHP.L",
          "name": "Primary Health Properties ",
          "ex_div_date": "2026-01-09",
          "pay_date": "2026-02-20",
          "dividend_per_share": "",
          "shares": "1467",
          "shares_at_exdiv": "1,457.00",
          "total_dividend": "0.00",
          "dividend_received": "",
          "status": "Estimated",
          "frequency": "Quarterly ",
          "notes": "",
          "logged_to_json": "FALSE"
        },
        {
          "Account": "TRADE212",
          "ticker": "FSFL.L",
          "name": "Foresight Solar Fund",
          "ex_div_date": "2026-01-23",
          "pay_date": "2026-02-20",
          "dividend_per_share": "0.02",
          "shares": "1633.219858",
          "shares_at_exdiv": "1633.219858",
          "total_dividend": "32.66",
          "dividend_received": "",
          "status": "Estimated",
          "frequency": "Quarterly ",
          "notes": "",
          "logged_to_json": "FALSE"
        },
        {
          "Account": "TRADE212",
          "ticker": "PHP.L",
          "name": "Primary Health Properties ",
          "ex_div_date": "2026-03-27",
          "pay_date": "2026-02-20",
          "dividend_per_share": "",
          "shares": "1467",
          "shares_at_exdiv": "1,457.00",
          "total_dividend": "0.00",
          "dividend_received": "",
          "status": "Estimated",
          "frequency": "Quarterly ",
          "notes": "",
          "logged_to_json": "FALSE"
        },
        {
          "Account": "TRADE212",
          "ticker": "SEQI.L",
          "name": "Sequoia Economic Infrastructure",
          "ex_div_date": "2026-01-30",
          "pay_date": "2026-02-27",
          "dividend_per_share": "",
          "shares": "300",
          "shares_at_exdiv": "300.00",
          "total_dividend": "0.00",
          "dividend_received": "",
          "status": "Estimated",
          "frequency": "Quarterly ",
          "notes": "",
          "logged_to_json": "FALSE"
        },
        {
          "Account": "TRADE212",
          "ticker": "GCP.L",
          "name": "GCP Infrastructure ",
          "ex_div_date": "2026-02-06",
          "pay_date": "2026-03-11",
          "dividend_per_share": "",
          "shares": "1000",
          "shares_at_exdiv": "1,000.00",
          "total_dividend": "0.00",
          "dividend_received": "",
          "status": "Estimated",
          "frequency": "Quarterly ",
          "notes": "",
          "logged_to_json": "FALSE"
        },
        {
          "Account": "IG ISA",
          "ticker": "IUKD.L",
          "name": "iShares Uk Dividend UCITS ETF",
          "ex_div_date": "2026-03-13",
          "pay_date": "2026-03-26",
          "dividend_per_share": "",
          "shares": "343",
          "shares_at_exdiv": "343.00",
          "total_dividend": "0.00",
          "dividend_received": "",
          "status": "Estimated",
          "frequency": "Quarterly ",
          "notes": "",
          "logged_to_json": "FALSE"
        },
        {
          "Account": "IG ISA",
          "ticker": "SUPR.L",
          "name": "Supermarket Income REIT PLC",
          "ex_div_date": "2026-01-30",
          "pay_date": "2026-03-27",
          "dividend_per_share": "",
          "shares": "8055",
          "shares_at_exdiv": "8,055.00",
          "total_dividend": "0.00",
          "dividend_received": "",
          "status": "Estimated",
          "frequency": "Quarterly ",
          "notes": "",
          "logged_to_json": "FALSE"
        },
        {
          "Account": "IG ISA",
          "ticker": "BP.L",
          "name": "BP PLC",
          "ex_div_date": "2026-02-20",
          "pay_date": "2026-03-27",
          "dividend_per_share": "",
          "shares": "707",
          "shares_at_exdiv": "707.00",
          "total_dividend": "0.00",
          "dividend_received": "",
          "status": "Estimated",
          "frequency": "Quarterly",
          "notes": "",
          "logged_to_json": "FALSE"
        },
        {
          "Account": "IG ISA",
          "ticker": "LAND.L",
          "name": "Land Securities",
          "ex_div_date": "2026-02-20",
          "pay_date": "2026-04-10",
          "dividend_per_share": "",
          "shares": "317",
          "shares_at_exdiv": "317.00",
          "total_dividend": "0.00",
          "dividend_received": "",
          "status": "Estimated",
          "frequency": "Quarterly",
          "notes": "",
          "logged_to_json": "FALSE"
        },
        {
          "Account": "IG ISA",
          "ticker": "MNG.L",
          "name": "M&G PLC",
          "ex_div_date": "2026-03-27",
          "pay_date": "2026-05-11",
          "dividend_per_share": "",
          "shares": "3916",
          "shares_at_exdiv": "3,916.00",
          "total_dividend": "0.00",
          "dividend_received": "",
          "status": "Estimated",
          "frequency": "Semi-Annual",
          "notes": "",
          "logged_to_json": "FALSE"
        },
        {
          "Account": "IG ISA",
          "ticker": "LLOY.L",
          "name": "Lloyds Banking Group PLC",
          "ex_div_date": "2026-04-10",
          "pay_date": "2026-05-20",
          "dividend_per_share": "",
          "shares": "606",
          "shares_at_exdiv": "606.00",
          "total_dividend": "0.00",
          "dividend_received": "",
          "status": "Estimated",
          "frequency": "Semi-Annual",
          "notes": "",
          "logged_to_json": "FALSE"
        },
        {
          "Account": "IG ISA",
          "ticker": "PHNX.L",
          "name": "Phoenix Group Holdings",
          "ex_div_date": "2026-04-03",
          "pay_date": "2026-05-21",
          "dividend_per_share": "",
          "shares": "1467",
          "shares_at_exdiv": "1,467.00",
          "total_dividend": "0.00",
          "dividend_received": "",
          "status": "Estimated",
          "frequency": "Semi-Annual",
          "notes": "",
          "logged_to_json": "FALSE"
        },
        {
          "Account": "TRADE212",
          "ticker": "FSFL.L",
          "name": "Foresight Solar Fund",
          "ex_div_date": "2026-04-24",
          "pay_date": "2026-05-22",
          "dividend_per_share": "0.02",
          "shares": "1633.219858",
          "shares_at_exdiv": "1633.219858",
          "total_dividend": "32.66",
          "dividend_received": "",
          "status": "Estimated",
          "frequency": "Quarterly ",
          "notes": "",
          "logged_to_json": "FALSE"
        },
        {
          "Account": "IG ISA",
          "ticker": "SUPR.L",
          "name": "Supermarket Income REIT PLC",
          "ex_div_date": "2026-04-24",
          "pay_date": "2026-05-22",
          "dividend_per_share": "",
          "shares": "8055",
          "shares_at_exdiv": "8,055.00",
          "total_dividend": "0.00",
          "dividend_received": "",
          "status": "Estimated",
          "frequency": "Quarterly ",
          "notes": "",
          "logged_to_json": "FALSE"
        },
        {
          "Account": "TRADE212",
          "ticker": "SEQI.L",
          "name": "Sequoia Economic Infrastructure",
          "ex_div_date": "2026-05-01",
          "pay_date": "2026-05-29",
          "dividend_per_share": "",
          "shares": "300",
          "shares_at_exdiv": "300.00",
          "total_dividend": "0.00",
          "dividend_received": "",
          "status": "Estimated",
          "frequency": "Quarterly ",
          "notes": "",
          "logged_to_json": "FALSE"
        },
        {
          "Account": "TRADE212",
          "ticker": "GCP.L",
          "name": "GCP Infrastructure ",
          "ex_div_date": "2026-05-08",
          "pay_date": "2026-06-04",
          "dividend_per_share": "",
          "shares": "1000",
          "shares_at_exdiv": "1,000.00",
          "total_dividend": "0.00",
          "dividend_received": "",
          "status": "Estimated",
          "frequency": "Quarterly ",
          "notes": "",
          "logged_to_json": "FALSE"
        },
        {
          "Account": "IG ISA",
          "ticker": "LGEN.L",
          "name": "Legal & General Group",
          "ex_div_date": "2026-04-24",
          "pay_date": "2026-06-05",
          "dividend_per_share": "",
          "shares": "3445",
          "shares_at_exdiv": "3,445.00",
          "total_dividend": "0.00",
          "dividend_received": "",
          "status": "Estimated",
          "frequency": "Semi-Annual",
          "notes": "",
          "logged_to_json": "FALSE"
        },
        {
          "Account": "IG ISA",
          "ticker": "BBOX.L",
          "name": "Tritax Big Box REIT PLC",
          "ex_div_date": "2026-05-22",
          "pay_date": "2026-06-12",
          "dividend_per_share": "",
          "shares": "350",
          "shares_at_exdiv": "350.00",
          "total_dividend": "0.00",
          "dividend_received": "",
          "status": "Estimated",
          "frequency": "Quarterly ",
          "notes": "",
          "logged_to_json": "FALSE"
        },
        {
          "Account": "IG ISA",
          "ticker": "IUKD.L",
          "name": "iShares Uk Dividend UCITS ETF",
          "ex_div_date": "2026-06-11",
          "pay_date": "2026-06-25",
          "dividend_per_share": "",
          "shares": "343",
          "shares_at_exdiv": "343.00",
          "total_dividend": "0.00",
          "dividend_received": "",
          "status": "Estimated",
          "frequency": "Quarterly ",
          "notes": "",
          "logged_to_json": "FALSE"
        },
        {
          "Account": "IG ISA",
          "ticker": "BP.L",
          "name": "BP PLC",
          "ex_div_date": "2026-05-15",
          "pay_date": "2026-06-26",
          "dividend_per_share": "",
          "shares": "707",
          "shares_at_exdiv": "707.00",
          "total_dividend": "0.00",
          "dividend_received": "",
          "status": "Estimated",
          "frequency": "Quarterly",
          "notes": "",
          "logged_to_json": "FALSE"
        },
        {
          "Account": "IG ISA",
          "ticker": "SVT.L",
          "name": "Severn Trent Plc",
          "ex_div_date": "2026-05-29",
          "pay_date": "2026-07-15",
          "dividend_per_share": "",
          "shares": "78",
          "shares_at_exdiv": "78.00",
          "total_dividend": "0.00",
          "dividend_received": "",
          "status": "Estimated",
          "frequency": "Semi-Annual",
          "notes": "",
          "logged_to_json": "FALSE"
        },
        {
          "Account": "IG ISA",
          "ticker": "NG.L",
          "name": "National Grid",
          "ex_div_date": "2026-05-29",
          "pay_date": "2026-07-17",
          "dividend_per_share": "",
          "shares": "192",
          "shares_at_exdiv": "192.00",
          "total_dividend": "0.00",
          "dividend_received": "",
          "status": "Estimated",
          "frequency": "Quarterly ",
          "notes": "",
          "logged_to_json": "FALSE"
        },
        {
          "Account": "IG ISA",
          "ticker": "LAND.L",
          "name": "Land Securities",
          "ex_div_date": "2026-06-12",
          "pay_date": "2026-07-24",
          "dividend_per_share": "",
          "shares": "317",
          "shares_at_exdiv": "317.00",
          "total_dividend": "0.00",
          "dividend_received": "",
          "status": "Estimated",
          "frequency": "Quarterly",
          "notes": "",
          "logged_to_json": "FALSE"
        },
        {
          "Account": "TRADE212",
          "ticker": "PHP.L",
          "name": "Primary Health Properties ",
          "ex_div_date": "2026-07-03",
          "pay_date": "2026-08-14",
          "dividend_per_share": "",
          "shares": "1467",
          "shares_at_exdiv": "1,457.00",
          "total_dividend": "0.00",
          "dividend_received": "",
          "status": "Estimated",
          "frequency": "Quarterly ",
          "notes": "",
          "logged_to_json": "FALSE"
        },
        {
          "Account": "TRADE212",
          "ticker": "SEQI.L",
          "name": "Sequoia Economic Infrastructure",
          "ex_div_date": "2026-07-24",
          "pay_date": "2026-08-21",
          "dividend_per_share": "",
          "shares": "300",
          "shares_at_exdiv": "300.00",
          "total_dividend": "0.00",
          "dividend_received": "",
          "status": "Estimated",
          "frequency": "Quarterly ",
          "notes": "",
          "logged_to_json": "FALSE"
        },
        {
          "Account": "TRADE212",
          "ticker": "FSFL.L",
          "name": "Foresight Solar Fund",
          "ex_div_date": "2026-07-24",
          "pay_date": "2026-08-21",
          "dividend_per_share": "",
          "shares": "924",
          "shares_at_exdiv": "924.00",
          "total_dividend": "0.00",
          "dividend_received": "",
          "status": "Estimated",
          "frequency": "Quarterly ",
          "notes": "",
          "logged_to_json": "FALSE"
        },
        {
          "Account": "TRADE212",
          "ticker": "GCP.L",
          "name": "GCP Infrastructure ",
          "ex_div_date": "2026-08-07",
          "pay_date": "2026-09-03",
          "dividend_per_share": "",
          "shares": "1000",
          "shares_at_exdiv": "1,000.00",
          "total_dividend": "0.00",
          "dividend_received": "",
          "status": "Estimated",
          "frequency": "Quarterly ",
          "notes": "",
          "logged_to_json": "FALSE"
        },
        {
          "Account": "IG ISA",
          "ticker": "BBOX.L",
          "name": "Tritax Big Box REIT PLC",
          "ex_div_date": "2026-08-14",
          "pay_date": "2026-09-07",
          "dividend_per_share": "",
          "shares": "350",
          "shares_at_exdiv": "350.00",
          "total_dividend": "0.00",
          "dividend_received": "",
          "status": "Estimated",
          "frequency": "Quarterly ",
          "notes": "",
          "logged_to_json": "FALSE"
        },
        {
          "Account": "IG ISA",
          "ticker": "LLOY.L",
          "name": "Lloyds Banking Group PLC",
          "ex_div_date": "2026-07-31",
          "pay_date": "2026-09-09",
          "dividend_per_share": "",
          "shares": "606",
          "shares_at_exdiv": "606.00",
          "total_dividend": "0.00",
          "dividend_received": "",
          "status": "Estimated",
          "frequency": "Semi-Annual",
          "notes": "",
          "logged_to_json": "FALSE"
        },
        {
          "Account": "IG ISA",
          "ticker": "BP.L",
          "name": "BP PLC",
          "ex_div_date": "2026-08-14",
          "pay_date": "2026-09-18",
          "dividend_per_share": "",
          "shares": "707",
          "shares_at_exdiv": "707.00",
          "total_dividend": "0.00",
          "dividend_received": "",
          "status": "Estimated",
          "frequency": "Quarterly",
          "notes": "",
          "logged_to_json": "FALSE"
        },
        {
          "Account": "IG ISA",
          "ticker": "IUKD.L",
          "name": "iShares Uk Dividend UCITS ETF",
          "ex_div_date": "2026-09-11",
          "pay_date": "2026-09-24",
          "dividend_per_share": "",
          "shares": "343",
          "shares_at_exdiv": "343.00",
          "total_dividend": "0.00",
          "dividend_received": "",
          "status": "Estimated",
          "frequency": "Quarterly ",
          "notes": "",
          "logged_to_json": "FALSE"
        },
        {
          "Account": "IG ISA",
          "ticker": "LAND.L",
          "name": "Land Securities",
          "ex_div_date": "2026-08-21",
          "pay_date": "2026-10-05",
          "dividend_per_share": "",
          "shares": "317",
          "shares_at_exdiv": "317.00",
          "total_dividend": "0.00",
          "dividend_received": "",
          "status": "Estimated",
          "frequency": "Quarterly",
          "notes": "",
          "logged_to_json": "FALSE"
        },
        {
          "Account": "IG ISA",
          "ticker": "SUPR.L",
          "name": "Supermarket Income REIT PLC",
          "ex_div_date": "2026-10-25",
          "pay_date": "2026-11-19",
          "dividend_per_share": "",
          "shares": "8055",
          "shares_at_exdiv": "8,055.00",
          "total_dividend": "0.00",
          "dividend_received": "",
          "status": "Estimated",
          "frequency": "Quarterly ",
          "notes": "",
          "logged_to_json": "FALSE"
        },
        {
          "Account": "IG ISA",
          "ticker": "ASHM.L",
          "name": "Ashmore Group PLC",
          "ex_div_date": "2026-03-27",
          "pay_date": "2026-12-08",
          "dividend_per_share": "",
          "shares": "620",
          "shares_at_exdiv": "620.00",
          "total_dividend": "0.00",
          "dividend_received": "",
          "status": "Estimated",
          "frequency": "Semi-Annual",
          "notes": "",
          "logged_to_json": "FALSE"
        }
      ],
      "next_five": [
        {
          "Account": "TRADE212",
          "ticker": "PHP.L",
          "name": "Primary Health Properties ",
          "ex_div_date": "2025-10-09",
          "pay_date": "2025-11-21",
          "dividend_per_share": "0.02",
          "shares": "299",
          "shares_at_exdiv": "299.00",
          "total_dividend": "5.98",
          "dividend_received": "",
          "status": "Confirmed",
          "frequency": "Quarterly ",
          "notes": "",
          "logged_to_json": "FALSE"
        },
        {
          "Account": "TRADE212",
          "ticker": "SEQI.L",
          "name": "Sequoia Economic Infrastructure",
          "ex_div_date": "2025-10-23",
          "pay_date": "2025-11-21",
          "dividend_per_share": "0.02",
          "shares": "300",
          "shares_at_exdiv": "300.00",
          "total_dividend": "6.00",
          "dividend_received": "",
          "status": "Confirmed",
          "frequency": "Quarterly ",
          "notes": "",
          "logged_to_json": "FALSE"
        },
        {
          "Account": "IG ISA",
          "ticker": "SUPR.L",
          "name": "Supermarket Income REIT PLC",
          "ex_div_date": "2025-10-23",
          "pay_date": "2025-11-21",
          "dividend_per_share": "0.02",
          "shares": "8055",
          "shares_at_exdiv": "8,055.00",
          "total_dividend": "124.05",
          "dividend_received": "",
          "status": "Confirmed",
          "frequency": "Quarterly ",
          "notes": "",
          "logged_to_json": "FALSE"
        },
        {
          "Account": "TRADE212",
          "ticker": "FSFL.L",
          "name": "Foresight Solar Fund",
          "ex_div_date": "2025-10-30",
          "pay_date": "2025-11-24",
          "dividend_per_share": "0.02",
          "shares": "1633.219858",
          "shares_at_exdiv": "1633.219858",
          "total_dividend": "32.66",
          "dividend_received": "",
          "status": "Confirmed",
          "frequency": "Quarterly ",
          "notes": "",
          "logged_to_json": "FALSE"
        },
        {
          "Account": "IG ISA",
          "ticker": "BBOX.L",
          "name": "Tritax Big Box REIT PLC",
          "ex_div_date": "2025-11-06",
          "pay_date": "2025-11-27",
          "dividend_per_share": "0.02",
          "shares": "350",
          "shares_at_exdiv": "350.00",
          "total_dividend": "6.70",
          "dividend_received": "",
          "status": "Confirmed",
          "frequency": "Quarterly ",
          "notes": "",
          "logged_to_json": "FALSE"
        }
      ],
      "monthly_totals": {
        "2021-02": 2.04,
        "2021-01": 3.4,
        "2021-03": 20.22,
        "2021-04": 23.880000000000003,
        "2021-05": 7.14,
        "2021-07": 497.28,
        "2021-11": 267.45,
        "2022-03": 8.620000000000001,
        "2022-04": 0.8899999999999999,
        "2025-09": 65.28999999999999,
        "2025-10": 401.22,
        "2025-11": 175.39,
        "2025-12": 170,
        "2026-01": 135.26,
        "2026-02": 184.98,
        "2026-03": 0,
        "2026-04": 0,
        "2026-12": 0,
        "2026-05": 32.66,
        "2026-06": 0,
        "2026-07": 0,
        "2026-08": 0,
        "2026-09": 0,
        "2026-10": 0,
        "2026-11": 0
      },
      "annual_total": null
    },
    "portfolio_summary": {
      "total_value": 0,
      "annual_income_gbp": 4265.04,
      "dividend_yield": 0
    },
    "ig_isa": {
      "balance": 0,
      "unrealised_gain": -54946.16,
      "gain_percent": -100,
      "annual_income": 4014.16
    },
    "trade212_isa": {
      "balance": 0,
      "unrealised_gain": -2751.74,
      "gain_percent": -100,
      "annual_income": 250.88
    }
  },
  "tesco": {
    "summary": {
      "sip_total_shares": 1619,
      "sip_value_gbp": 7186.74,
      "sip_average_cost": 2.69,
      "sip_gain_gbp": 2833.06,
      "saye_total_options": 14363,
      "saye_option_price": 2.2,
      "saye_current_value_gbp": 63757.35,
      "saye_potential_gain_gbp": 32158.75,
      "combined_value_gbp": 70944.09,
      "combined_gain_gbp": 34991.81
    },
    "isa_migration_plan": {
      "maturity_date": "2029-03-01",
      "tax_years": {
        "2028_2029": "NO ISA contributions allowed (SAYE exercise year).",
        "2029_2030": "£20,000 transferred into ISA.",
        "2030_2031": "£20,000 transferred into ISA.",
        "2031_2032": "Remaining ~£23,000 transferred."
      }
    }
  },
  "reits_outlook": {
    "SUPR": {
      "status": "🟢 Stable",
      "notes": "Discount narrowing, dividends well covered, strong supermarket tenant base."
    },
    "PHP": {
      "status": "🟢 Healthy",
      "notes": "NHS-backed income, low-risk, strong long-term outlook."
    },
    "FSFL": {
      "status": "🟡 Moderate",
      "notes": "Renewable sector pressured by rates; dividend stable but NAV under pressure."
    },
    "GCP": {
      "status": "🟡 Cautious",
      "notes": "Discount large; income strong but NAV volatility continues."
    },
    "RGL": {
      "status": "🟡 Risky",
      "notes": "High yield but sector struggling. Income good but property values uncertain."
    }
  },
  "financials_outlook": {
    "MNG.GB": {
      "status": "🟢 Strong",
      "notes": "High yield, stable performance, strong solvency ratios."
    },
    "LGEN.GB": {
      "status": "🟢 Strong",
      "notes": "Very reliable dividend payer, long-term income compounder."
    },
    "PHNX.GB": {
      "status": "🟡 Watchlist",
      "notes": "Dividend huge but payout high; risk depends on interest-rate outlook."
    }
  },
  "dividend_planner": {
    "monthly_breakdown": {
      "Jan": 135.26,
      "Feb": 184.98,
      "Mar": 0,
      "Apr": 0,
      "May": 32.66,
      "Jun": 0,
      "Jul": 0,
      "Aug": 0,
      "Sep": 65.29,
      "Oct": 401.22,
      "Nov": 175.39,
      "Dec": 170
    },
    "forecast_total": 1164.8,
    "received_ytd": 576.51
  },
  "meta": {
    "last_updated": "2025-11-20 08:53:17",
    "source": "Aurora ISA Sync (Watchlist Live Prices)"
  }
}
